[
 {
   "zone_id": 1,
   "country_code": "AD",
   "zone_name": "Europe/Andorra"
 },
 {
   "zone_id": 2,
   "country_code": "AE",
   "zone_name": "Asia/Dubai"
 },
 {
   "zone_id": 3,
   "country_code": "AF",
   "zone_name": "Asia/Kabul"
 },
 {
   "zone_id": 4,
   "country_code": "AG",
   "zone_name": "America/Antigua"
 },
 {
   "zone_id": 5,
   "country_code": "AI",
   "zone_name": "America/Anguilla"
 },
 {
   "zone_id": 6,
   "country_code": "AL",
   "zone_name": "Europe/Tirane"
 },
 {
   "zone_id": 7,
   "country_code": "AM",
   "zone_name": "Asia/Yerevan"
 },
 {
   "zone_id": 8,
   "country_code": "AO",
   "zone_name": "Africa/Luanda"
 },
 {
   "zone_id": 9,
   "country_code": "AQ",
   "zone_name": "Antarctica/McMurdo"
 },
 {
   "zone_id": 10,
   "country_code": "AQ",
   "zone_name": "Antarctica/Casey"
 },
 {
   "zone_id": 11,
   "country_code": "AQ",
   "zone_name": "Antarctica/Davis"
 },
 {
   "zone_id": 12,
   "country_code": "AQ",
   "zone_name": "Antarctica/DumontDUrville"
 },
 {
   "zone_id": 13,
   "country_code": "AQ",
   "zone_name": "Antarctica/Mawson"
 },
 {
   "zone_id": 14,
   "country_code": "AQ",
   "zone_name": "Antarctica/Palmer"
 },
 {
   "zone_id": 15,
   "country_code": "AQ",
   "zone_name": "Antarctica/Rothera"
 },
 {
   "zone_id": 16,
   "country_code": "AQ",
   "zone_name": "Antarctica/Syowa"
 },
 {
   "zone_id": 17,
   "country_code": "AQ",
   "zone_name": "Antarctica/Troll"
 },
 {
   "zone_id": 18,
   "country_code": "AQ",
   "zone_name": "Antarctica/Vostok"
 },
 {
   "zone_id": 19,
   "country_code": "AR",
   "zone_name": "America/Argentina/Buenos_Aires"
 },
 {
   "zone_id": 20,
   "country_code": "AR",
   "zone_name": "America/Argentina/Cordoba"
 },
 {
   "zone_id": 21,
   "country_code": "AR",
   "zone_name": "America/Argentina/Salta"
 },
 {
   "zone_id": 22,
   "country_code": "AR",
   "zone_name": "America/Argentina/Jujuy"
 },
 {
   "zone_id": 23,
   "country_code": "AR",
   "zone_name": "America/Argentina/Tucuman"
 },
 {
   "zone_id": 24,
   "country_code": "AR",
   "zone_name": "America/Argentina/Catamarca"
 },
 {
   "zone_id": 25,
   "country_code": "AR",
   "zone_name": "America/Argentina/La_Rioja"
 },
 {
   "zone_id": 26,
   "country_code": "AR",
   "zone_name": "America/Argentina/San_Juan"
 },
 {
   "zone_id": 27,
   "country_code": "AR",
   "zone_name": "America/Argentina/Mendoza"
 },
 {
   "zone_id": 28,
   "country_code": "AR",
   "zone_name": "America/Argentina/San_Luis"
 },
 {
   "zone_id": 29,
   "country_code": "AR",
   "zone_name": "America/Argentina/Rio_Gallegos"
 },
 {
   "zone_id": 30,
   "country_code": "AR",
   "zone_name": "America/Argentina/Ushuaia"
 },
 {
   "zone_id": 31,
   "country_code": "AS",
   "zone_name": "Pacific/Pago_Pago"
 },
 {
   "zone_id": 32,
   "country_code": "AT",
   "zone_name": "Europe/Vienna"
 },
 {
   "zone_id": 33,
   "country_code": "AU",
   "zone_name": "Australia/Lord_Howe"
 },
 {
   "zone_id": 34,
   "country_code": "AU",
   "zone_name": "Antarctica/Macquarie"
 },
 {
   "zone_id": 35,
   "country_code": "AU",
   "zone_name": "Australia/Hobart"
 },
 {
   "zone_id": 36,
   "country_code": "AU",
   "zone_name": "Australia/Currie"
 },
 {
   "zone_id": 37,
   "country_code": "AU",
   "zone_name": "Australia/Melbourne"
 },
 {
   "zone_id": 38,
   "country_code": "AU",
   "zone_name": "Australia/Sydney"
 },
 {
   "zone_id": 39,
   "country_code": "AU",
   "zone_name": "Australia/Broken_Hill"
 },
 {
   "zone_id": 40,
   "country_code": "AU",
   "zone_name": "Australia/Brisbane"
 },
 {
   "zone_id": 41,
   "country_code": "AU",
   "zone_name": "Australia/Lindeman"
 },
 {
   "zone_id": 42,
   "country_code": "AU",
   "zone_name": "Australia/Adelaide"
 },
 {
   "zone_id": 43,
   "country_code": "AU",
   "zone_name": "Australia/Darwin"
 },
 {
   "zone_id": 44,
   "country_code": "AU",
   "zone_name": "Australia/Perth"
 },
 {
   "zone_id": 45,
   "country_code": "AU",
   "zone_name": "Australia/Eucla"
 },
 {
   "zone_id": 46,
   "country_code": "AW",
   "zone_name": "America/Aruba"
 },
 {
   "zone_id": 47,
   "country_code": "AX",
   "zone_name": "Europe/Mariehamn"
 },
 {
   "zone_id": 48,
   "country_code": "AZ",
   "zone_name": "Asia/Baku"
 },
 {
   "zone_id": 49,
   "country_code": "BA",
   "zone_name": "Europe/Sarajevo"
 },
 {
   "zone_id": 50,
   "country_code": "BB",
   "zone_name": "America/Barbados"
 },
 {
   "zone_id": 51,
   "country_code": "BD",
   "zone_name": "Asia/Dhaka"
 },
 {
   "zone_id": 52,
   "country_code": "BE",
   "zone_name": "Europe/Brussels"
 },
 {
   "zone_id": 53,
   "country_code": "BF",
   "zone_name": "Africa/Ouagadougou"
 },
 {
   "zone_id": 54,
   "country_code": "BG",
   "zone_name": "Europe/Sofia"
 },
 {
   "zone_id": 55,
   "country_code": "BH",
   "zone_name": "Asia/Bahrain"
 },
 {
   "zone_id": 56,
   "country_code": "BI",
   "zone_name": "Africa/Bujumbura"
 },
 {
   "zone_id": 57,
   "country_code": "BJ",
   "zone_name": "Africa/Porto-Novo"
 },
 {
   "zone_id": 58,
   "country_code": "BL",
   "zone_name": "America/St_Barthelemy"
 },
 {
   "zone_id": 59,
   "country_code": "BM",
   "zone_name": "Atlantic/Bermuda"
 },
 {
   "zone_id": 60,
   "country_code": "BN",
   "zone_name": "Asia/Brunei"
 },
 {
   "zone_id": 61,
   "country_code": "BO",
   "zone_name": "America/La_Paz"
 },
 {
   "zone_id": 62,
   "country_code": "BQ",
   "zone_name": "America/Kralendijk"
 },
 {
   "zone_id": 63,
   "country_code": "BR",
   "zone_name": "America/Noronha"
 },
 {
   "zone_id": 64,
   "country_code": "BR",
   "zone_name": "America/Belem"
 },
 {
   "zone_id": 65,
   "country_code": "BR",
   "zone_name": "America/Fortaleza"
 },
 {
   "zone_id": 66,
   "country_code": "BR",
   "zone_name": "America/Recife"
 },
 {
   "zone_id": 67,
   "country_code": "BR",
   "zone_name": "America/Araguaina"
 },
 {
   "zone_id": 68,
   "country_code": "BR",
   "zone_name": "America/Maceio"
 },
 {
   "zone_id": 69,
   "country_code": "BR",
   "zone_name": "America/Bahia"
 },
 {
   "zone_id": 70,
   "country_code": "BR",
   "zone_name": "America/Sao_Paulo"
 },
 {
   "zone_id": 71,
   "country_code": "BR",
   "zone_name": "America/Campo_Grande"
 },
 {
   "zone_id": 72,
   "country_code": "BR",
   "zone_name": "America/Cuiaba"
 },
 {
   "zone_id": 73,
   "country_code": "BR",
   "zone_name": "America/Santarem"
 },
 {
   "zone_id": 74,
   "country_code": "BR",
   "zone_name": "America/Porto_Velho"
 },
 {
   "zone_id": 75,
   "country_code": "BR",
   "zone_name": "America/Boa_Vista"
 },
 {
   "zone_id": 76,
   "country_code": "BR",
   "zone_name": "America/Manaus"
 },
 {
   "zone_id": 77,
   "country_code": "BR",
   "zone_name": "America/Eirunepe"
 },
 {
   "zone_id": 78,
   "country_code": "BR",
   "zone_name": "America/Rio_Branco"
 },
 {
   "zone_id": 79,
   "country_code": "BS",
   "zone_name": "America/Nassau"
 },
 {
   "zone_id": 80,
   "country_code": "BT",
   "zone_name": "Asia/Thimphu"
 },
 {
   "zone_id": 81,
   "country_code": "BW",
   "zone_name": "Africa/Gaborone"
 },
 {
   "zone_id": 82,
   "country_code": "BY",
   "zone_name": "Europe/Minsk"
 },
 {
   "zone_id": 83,
   "country_code": "BZ",
   "zone_name": "America/Belize"
 },
 {
   "zone_id": 84,
   "country_code": "CA",
   "zone_name": "America/St_Johns"
 },
 {
   "zone_id": 85,
   "country_code": "CA",
   "zone_name": "America/Halifax"
 },
 {
   "zone_id": 86,
   "country_code": "CA",
   "zone_name": "America/Glace_Bay"
 },
 {
   "zone_id": 87,
   "country_code": "CA",
   "zone_name": "America/Moncton"
 },
 {
   "zone_id": 88,
   "country_code": "CA",
   "zone_name": "America/Goose_Bay"
 },
 {
   "zone_id": 89,
   "country_code": "CA",
   "zone_name": "America/Blanc-Sablon"
 },
 {
   "zone_id": 90,
   "country_code": "CA",
   "zone_name": "America/Toronto"
 },
 {
   "zone_id": 91,
   "country_code": "CA",
   "zone_name": "America/Nipigon"
 },
 {
   "zone_id": 92,
   "country_code": "CA",
   "zone_name": "America/Thunder_Bay"
 },
 {
   "zone_id": 93,
   "country_code": "CA",
   "zone_name": "America/Iqaluit"
 },
 {
   "zone_id": 94,
   "country_code": "CA",
   "zone_name": "America/Pangnirtung"
 },
 {
   "zone_id": 95,
   "country_code": "CA",
   "zone_name": "America/Atikokan"
 },
 {
   "zone_id": 96,
   "country_code": "CA",
   "zone_name": "America/Winnipeg"
 },
 {
   "zone_id": 97,
   "country_code": "CA",
   "zone_name": "America/Rainy_River"
 },
 {
   "zone_id": 98,
   "country_code": "CA",
   "zone_name": "America/Resolute"
 },
 {
   "zone_id": 99,
   "country_code": "CA",
   "zone_name": "America/Rankin_Inlet"
 },
 {
   "zone_id": 100,
   "country_code": "CA",
   "zone_name": "America/Regina"
 },
 {
   "zone_id": 101,
   "country_code": "CA",
   "zone_name": "America/Swift_Current"
 },
 {
   "zone_id": 102,
   "country_code": "CA",
   "zone_name": "America/Edmonton"
 },
 {
   "zone_id": 103,
   "country_code": "CA",
   "zone_name": "America/Cambridge_Bay"
 },
 {
   "zone_id": 104,
   "country_code": "CA",
   "zone_name": "America/Yellowknife"
 },
 {
   "zone_id": 105,
   "country_code": "CA",
   "zone_name": "America/Inuvik"
 },
 {
   "zone_id": 106,
   "country_code": "CA",
   "zone_name": "America/Creston"
 },
 {
   "zone_id": 107,
   "country_code": "CA",
   "zone_name": "America/Dawson_Creek"
 },
 {
   "zone_id": 108,
   "country_code": "CA",
   "zone_name": "America/Fort_Nelson"
 },
 {
   "zone_id": 109,
   "country_code": "CA",
   "zone_name": "America/Vancouver"
 },
 {
   "zone_id": 110,
   "country_code": "CA",
   "zone_name": "America/Whitehorse"
 },
 {
   "zone_id": 111,
   "country_code": "CA",
   "zone_name": "America/Dawson"
 },
 {
   "zone_id": 112,
   "country_code": "CC",
   "zone_name": "Indian/Cocos"
 },
 {
   "zone_id": 113,
   "country_code": "CD",
   "zone_name": "Africa/Kinshasa"
 },
 {
   "zone_id": 114,
   "country_code": "CD",
   "zone_name": "Africa/Lubumbashi"
 },
 {
   "zone_id": 115,
   "country_code": "CF",
   "zone_name": "Africa/Bangui"
 },
 {
   "zone_id": 116,
   "country_code": "CG",
   "zone_name": "Africa/Brazzaville"
 },
 {
   "zone_id": 117,
   "country_code": "CH",
   "zone_name": "Europe/Zurich"
 },
 {
   "zone_id": 118,
   "country_code": "CI",
   "zone_name": "Africa/Abidjan"
 },
 {
   "zone_id": 119,
   "country_code": "CK",
   "zone_name": "Pacific/Rarotonga"
 },
 {
   "zone_id": 120,
   "country_code": "CL",
   "zone_name": "America/Santiago"
 },
 {
   "zone_id": 121,
   "country_code": "CL",
   "zone_name": "America/Punta_Arenas"
 },
 {
   "zone_id": 122,
   "country_code": "CL",
   "zone_name": "Pacific/Easter"
 },
 {
   "zone_id": 123,
   "country_code": "CM",
   "zone_name": "Africa/Douala"
 },
 {
   "zone_id": 124,
   "country_code": "CN",
   "zone_name": "Asia/Shanghai"
 },
 {
   "zone_id": 125,
   "country_code": "CN",
   "zone_name": "Asia/Urumqi"
 },
 {
   "zone_id": 126,
   "country_code": "CO",
   "zone_name": "America/Bogota"
 },
 {
   "zone_id": 127,
   "country_code": "CR",
   "zone_name": "America/Costa_Rica"
 },
 {
   "zone_id": 128,
   "country_code": "CU",
   "zone_name": "America/Havana"
 },
 {
   "zone_id": 129,
   "country_code": "CV",
   "zone_name": "Atlantic/Cape_Verde"
 },
 {
   "zone_id": 130,
   "country_code": "CW",
   "zone_name": "America/Curacao"
 },
 {
   "zone_id": 131,
   "country_code": "CX",
   "zone_name": "Indian/Christmas"
 },
 {
   "zone_id": 132,
   "country_code": "CY",
   "zone_name": "Asia/Nicosia"
 },
 {
   "zone_id": 133,
   "country_code": "CY",
   "zone_name": "Asia/Famagusta"
 },
 {
   "zone_id": 134,
   "country_code": "CZ",
   "zone_name": "Europe/Prague"
 },
 {
   "zone_id": 135,
   "country_code": "DE",
   "zone_name": "Europe/Berlin"
 },
 {
   "zone_id": 136,
   "country_code": "DE",
   "zone_name": "Europe/Busingen"
 },
 {
   "zone_id": 137,
   "country_code": "DJ",
   "zone_name": "Africa/Djibouti"
 },
 {
   "zone_id": 138,
   "country_code": "DK",
   "zone_name": "Europe/Copenhagen"
 },
 {
   "zone_id": 139,
   "country_code": "DM",
   "zone_name": "America/Dominica"
 },
 {
   "zone_id": 140,
   "country_code": "DO",
   "zone_name": "America/Santo_Domingo"
 },
 {
   "zone_id": 141,
   "country_code": "DZ",
   "zone_name": "Africa/Algiers"
 },
 {
   "zone_id": 142,
   "country_code": "EC",
   "zone_name": "America/Guayaquil"
 },
 {
   "zone_id": 143,
   "country_code": "EC",
   "zone_name": "Pacific/Galapagos"
 },
 {
   "zone_id": 144,
   "country_code": "EE",
   "zone_name": "Europe/Tallinn"
 },
 {
   "zone_id": 145,
   "country_code": "EG",
   "zone_name": "Africa/Cairo"
 },
 {
   "zone_id": 146,
   "country_code": "EH",
   "zone_name": "Africa/El_Aaiun"
 },
 {
   "zone_id": 147,
   "country_code": "ER",
   "zone_name": "Africa/Asmara"
 },
 {
   "zone_id": 148,
   "country_code": "ES",
   "zone_name": "Europe/Madrid"
 },
 {
   "zone_id": 149,
   "country_code": "ES",
   "zone_name": "Africa/Ceuta"
 },
 {
   "zone_id": 150,
   "country_code": "ES",
   "zone_name": "Atlantic/Canary"
 },
 {
   "zone_id": 151,
   "country_code": "ET",
   "zone_name": "Africa/Addis_Ababa"
 },
 {
   "zone_id": 152,
   "country_code": "FI",
   "zone_name": "Europe/Helsinki"
 },
 {
   "zone_id": 153,
   "country_code": "FJ",
   "zone_name": "Pacific/Fiji"
 },
 {
   "zone_id": 154,
   "country_code": "FK",
   "zone_name": "Atlantic/Stanley"
 },
 {
   "zone_id": 155,
   "country_code": "FM",
   "zone_name": "Pacific/Chuuk"
 },
 {
   "zone_id": 156,
   "country_code": "FM",
   "zone_name": "Pacific/Pohnpei"
 },
 {
   "zone_id": 157,
   "country_code": "FM",
   "zone_name": "Pacific/Kosrae"
 },
 {
   "zone_id": 158,
   "country_code": "FO",
   "zone_name": "Atlantic/Faroe"
 },
 {
   "zone_id": 159,
   "country_code": "FR",
   "zone_name": "Europe/Paris"
 },
 {
   "zone_id": 160,
   "country_code": "GA",
   "zone_name": "Africa/Libreville"
 },
 {
   "zone_id": 161,
   "country_code": "GB",
   "zone_name": "Europe/London"
 },
 {
   "zone_id": 162,
   "country_code": "GD",
   "zone_name": "America/Grenada"
 },
 {
   "zone_id": 163,
   "country_code": "GE",
   "zone_name": "Asia/Tbilisi"
 },
 {
   "zone_id": 164,
   "country_code": "GF",
   "zone_name": "America/Cayenne"
 },
 {
   "zone_id": 165,
   "country_code": "GG",
   "zone_name": "Europe/Guernsey"
 },
 {
   "zone_id": 166,
   "country_code": "GH",
   "zone_name": "Africa/Accra"
 },
 {
   "zone_id": 167,
   "country_code": "GI",
   "zone_name": "Europe/Gibraltar"
 },
 {
   "zone_id": 168,
   "country_code": "GL",
   "zone_name": "America/Godthab"
 },
 {
   "zone_id": 169,
   "country_code": "GL",
   "zone_name": "America/Danmarkshavn"
 },
 {
   "zone_id": 170,
   "country_code": "GL",
   "zone_name": "America/Scoresbysund"
 },
 {
   "zone_id": 171,
   "country_code": "GL",
   "zone_name": "America/Thule"
 },
 {
   "zone_id": 172,
   "country_code": "GM",
   "zone_name": "Africa/Banjul"
 },
 {
   "zone_id": 173,
   "country_code": "GN",
   "zone_name": "Africa/Conakry"
 },
 {
   "zone_id": 174,
   "country_code": "GP",
   "zone_name": "America/Guadeloupe"
 },
 {
   "zone_id": 175,
   "country_code": "GQ",
   "zone_name": "Africa/Malabo"
 },
 {
   "zone_id": 176,
   "country_code": "GR",
   "zone_name": "Europe/Athens"
 },
 {
   "zone_id": 177,
   "country_code": "GS",
   "zone_name": "Atlantic/South_Georgia"
 },
 {
   "zone_id": 178,
   "country_code": "GT",
   "zone_name": "America/Guatemala"
 },
 {
   "zone_id": 179,
   "country_code": "GU",
   "zone_name": "Pacific/Guam"
 },
 {
   "zone_id": 180,
   "country_code": "GW",
   "zone_name": "Africa/Bissau"
 },
 {
   "zone_id": 181,
   "country_code": "GY",
   "zone_name": "America/Guyana"
 },
 {
   "zone_id": 182,
   "country_code": "HK",
   "zone_name": "Asia/Hong_Kong"
 },
 {
   "zone_id": 183,
   "country_code": "HN",
   "zone_name": "America/Tegucigalpa"
 },
 {
   "zone_id": 184,
   "country_code": "HR",
   "zone_name": "Europe/Zagreb"
 },
 {
   "zone_id": 185,
   "country_code": "HT",
   "zone_name": "America/Port-au-Prince"
 },
 {
   "zone_id": 186,
   "country_code": "HU",
   "zone_name": "Europe/Budapest"
 },
 {
   "zone_id": 187,
   "country_code": "ID",
   "zone_name": "Asia/Jakarta"
 },
 {
   "zone_id": 188,
   "country_code": "ID",
   "zone_name": "Asia/Pontianak"
 },
 {
   "zone_id": 189,
   "country_code": "ID",
   "zone_name": "Asia/Makassar"
 },
 {
   "zone_id": 190,
   "country_code": "ID",
   "zone_name": "Asia/Jayapura"
 },
 {
   "zone_id": 191,
   "country_code": "IE",
   "zone_name": "Europe/Dublin"
 },
 {
   "zone_id": 192,
   "country_code": "IL",
   "zone_name": "Asia/Jerusalem"
 },
 {
   "zone_id": 193,
   "country_code": "IM",
   "zone_name": "Europe/Isle_of_Man"
 },
 {
   "zone_id": 194,
   "country_code": "IN",
   "zone_name": "Asia/Kolkata"
 },
 {
   "zone_id": 195,
   "country_code": "IO",
   "zone_name": "Indian/Chagos"
 },
 {
   "zone_id": 196,
   "country_code": "IQ",
   "zone_name": "Asia/Baghdad"
 },
 {
   "zone_id": 197,
   "country_code": "IR",
   "zone_name": "Asia/Tehran"
 },
 {
   "zone_id": 198,
   "country_code": "IS",
   "zone_name": "Atlantic/Reykjavik"
 },
 {
   "zone_id": 199,
   "country_code": "IT",
   "zone_name": "Europe/Rome"
 },
 {
   "zone_id": 200,
   "country_code": "JE",
   "zone_name": "Europe/Jersey"
 },
 {
   "zone_id": 201,
   "country_code": "JM",
   "zone_name": "America/Jamaica"
 },
 {
   "zone_id": 202,
   "country_code": "JO",
   "zone_name": "Asia/Amman"
 },
 {
   "zone_id": 203,
   "country_code": "JP",
   "zone_name": "Asia/Tokyo"
 },
 {
   "zone_id": 204,
   "country_code": "KE",
   "zone_name": "Africa/Nairobi"
 },
 {
   "zone_id": 205,
   "country_code": "KG",
   "zone_name": "Asia/Bishkek"
 },
 {
   "zone_id": 206,
   "country_code": "KH",
   "zone_name": "Asia/Phnom_Penh"
 },
 {
   "zone_id": 207,
   "country_code": "KI",
   "zone_name": "Pacific/Tarawa"
 },
 {
   "zone_id": 208,
   "country_code": "KI",
   "zone_name": "Pacific/Enderbury"
 },
 {
   "zone_id": 209,
   "country_code": "KI",
   "zone_name": "Pacific/Kiritimati"
 },
 {
   "zone_id": 210,
   "country_code": "KM",
   "zone_name": "Indian/Comoro"
 },
 {
   "zone_id": 211,
   "country_code": "KN",
   "zone_name": "America/St_Kitts"
 },
 {
   "zone_id": 212,
   "country_code": "KP",
   "zone_name": "Asia/Pyongyang"
 },
 {
   "zone_id": 213,
   "country_code": "KR",
   "zone_name": "Asia/Seoul"
 },
 {
   "zone_id": 214,
   "country_code": "KW",
   "zone_name": "Asia/Kuwait"
 },
 {
   "zone_id": 215,
   "country_code": "KY",
   "zone_name": "America/Cayman"
 },
 {
   "zone_id": 216,
   "country_code": "KZ",
   "zone_name": "Asia/Almaty"
 },
 {
   "zone_id": 217,
   "country_code": "KZ",
   "zone_name": "Asia/Qyzylorda"
 },
 {
   "zone_id": 218,
   "country_code": "KZ",
   "zone_name": "Asia/Aqtobe"
 },
 {
   "zone_id": 219,
   "country_code": "KZ",
   "zone_name": "Asia/Aqtau"
 },
 {
   "zone_id": 220,
   "country_code": "KZ",
   "zone_name": "Asia/Atyrau"
 },
 {
   "zone_id": 221,
   "country_code": "KZ",
   "zone_name": "Asia/Oral"
 },
 {
   "zone_id": 222,
   "country_code": "LA",
   "zone_name": "Asia/Vientiane"
 },
 {
   "zone_id": 223,
   "country_code": "LB",
   "zone_name": "Asia/Beirut"
 },
 {
   "zone_id": 224,
   "country_code": "LC",
   "zone_name": "America/St_Lucia"
 },
 {
   "zone_id": 225,
   "country_code": "LI",
   "zone_name": "Europe/Vaduz"
 },
 {
   "zone_id": 226,
   "country_code": "LK",
   "zone_name": "Asia/Colombo"
 },
 {
   "zone_id": 227,
   "country_code": "LR",
   "zone_name": "Africa/Monrovia"
 },
 {
   "zone_id": 228,
   "country_code": "LS",
   "zone_name": "Africa/Maseru"
 },
 {
   "zone_id": 229,
   "country_code": "LT",
   "zone_name": "Europe/Vilnius"
 },
 {
   "zone_id": 230,
   "country_code": "LU",
   "zone_name": "Europe/Luxembourg"
 },
 {
   "zone_id": 231,
   "country_code": "LV",
   "zone_name": "Europe/Riga"
 },
 {
   "zone_id": 232,
   "country_code": "LY",
   "zone_name": "Africa/Tripoli"
 },
 {
   "zone_id": 233,
   "country_code": "MA",
   "zone_name": "Africa/Casablanca"
 },
 {
   "zone_id": 234,
   "country_code": "MC",
   "zone_name": "Europe/Monaco"
 },
 {
   "zone_id": 235,
   "country_code": "MD",
   "zone_name": "Europe/Chisinau"
 },
 {
   "zone_id": 236,
   "country_code": "ME",
   "zone_name": "Europe/Podgorica"
 },
 {
   "zone_id": 237,
   "country_code": "MF",
   "zone_name": "America/Marigot"
 },
 {
   "zone_id": 238,
   "country_code": "MG",
   "zone_name": "Indian/Antananarivo"
 },
 {
   "zone_id": 239,
   "country_code": "MH",
   "zone_name": "Pacific/Majuro"
 },
 {
   "zone_id": 240,
   "country_code": "MH",
   "zone_name": "Pacific/Kwajalein"
 },
 {
   "zone_id": 241,
   "country_code": "MK",
   "zone_name": "Europe/Skopje"
 },
 {
   "zone_id": 242,
   "country_code": "ML",
   "zone_name": "Africa/Bamako"
 },
 {
   "zone_id": 243,
   "country_code": "MM",
   "zone_name": "Asia/Yangon"
 },
 {
   "zone_id": 244,
   "country_code": "MN",
   "zone_name": "Asia/Ulaanbaatar"
 },
 {
   "zone_id": 245,
   "country_code": "MN",
   "zone_name": "Asia/Hovd"
 },
 {
   "zone_id": 246,
   "country_code": "MN",
   "zone_name": "Asia/Choibalsan"
 },
 {
   "zone_id": 247,
   "country_code": "MO",
   "zone_name": "Asia/Macau"
 },
 {
   "zone_id": 248,
   "country_code": "MP",
   "zone_name": "Pacific/Saipan"
 },
 {
   "zone_id": 249,
   "country_code": "MQ",
   "zone_name": "America/Martinique"
 },
 {
   "zone_id": 250,
   "country_code": "MR",
   "zone_name": "Africa/Nouakchott"
 },
 {
   "zone_id": 251,
   "country_code": "MS",
   "zone_name": "America/Montserrat"
 },
 {
   "zone_id": 252,
   "country_code": "MT",
   "zone_name": "Europe/Malta"
 },
 {
   "zone_id": 253,
   "country_code": "MU",
   "zone_name": "Indian/Mauritius"
 },
 {
   "zone_id": 254,
   "country_code": "MV",
   "zone_name": "Indian/Maldives"
 },
 {
   "zone_id": 255,
   "country_code": "MW",
   "zone_name": "Africa/Blantyre"
 },
 {
   "zone_id": 256,
   "country_code": "MX",
   "zone_name": "America/Mexico_City"
 },
 {
   "zone_id": 257,
   "country_code": "MX",
   "zone_name": "America/Cancun"
 },
 {
   "zone_id": 258,
   "country_code": "MX",
   "zone_name": "America/Merida"
 },
 {
   "zone_id": 259,
   "country_code": "MX",
   "zone_name": "America/Monterrey"
 },
 {
   "zone_id": 260,
   "country_code": "MX",
   "zone_name": "America/Matamoros"
 },
 {
   "zone_id": 261,
   "country_code": "MX",
   "zone_name": "America/Mazatlan"
 },
 {
   "zone_id": 262,
   "country_code": "MX",
   "zone_name": "America/Chihuahua"
 },
 {
   "zone_id": 263,
   "country_code": "MX",
   "zone_name": "America/Ojinaga"
 },
 {
   "zone_id": 264,
   "country_code": "MX",
   "zone_name": "America/Hermosillo"
 },
 {
   "zone_id": 265,
   "country_code": "MX",
   "zone_name": "America/Tijuana"
 },
 {
   "zone_id": 266,
   "country_code": "MX",
   "zone_name": "America/Bahia_Banderas"
 },
 {
   "zone_id": 267,
   "country_code": "MY",
   "zone_name": "Asia/Kuala_Lumpur"
 },
 {
   "zone_id": 268,
   "country_code": "MY",
   "zone_name": "Asia/Kuching"
 },
 {
   "zone_id": 269,
   "country_code": "MZ",
   "zone_name": "Africa/Maputo"
 },
 {
   "zone_id": 270,
   "country_code": "NA",
   "zone_name": "Africa/Windhoek"
 },
 {
   "zone_id": 271,
   "country_code": "NC",
   "zone_name": "Pacific/Noumea"
 },
 {
   "zone_id": 272,
   "country_code": "NE",
   "zone_name": "Africa/Niamey"
 },
 {
   "zone_id": 273,
   "country_code": "NF",
   "zone_name": "Pacific/Norfolk"
 },
 {
   "zone_id": 274,
   "country_code": "NG",
   "zone_name": "Africa/Lagos"
 },
 {
   "zone_id": 275,
   "country_code": "NI",
   "zone_name": "America/Managua"
 },
 {
   "zone_id": 276,
   "country_code": "NL",
   "zone_name": "Europe/Amsterdam"
 },
 {
   "zone_id": 277,
   "country_code": "NO",
   "zone_name": "Europe/Oslo"
 },
 {
   "zone_id": 278,
   "country_code": "NP",
   "zone_name": "Asia/Kathmandu"
 },
 {
   "zone_id": 279,
   "country_code": "NR",
   "zone_name": "Pacific/Nauru"
 },
 {
   "zone_id": 280,
   "country_code": "NU",
   "zone_name": "Pacific/Niue"
 },
 {
   "zone_id": 281,
   "country_code": "NZ",
   "zone_name": "Pacific/Auckland"
 },
 {
   "zone_id": 282,
   "country_code": "NZ",
   "zone_name": "Pacific/Chatham"
 },
 {
   "zone_id": 283,
   "country_code": "OM",
   "zone_name": "Asia/Muscat"
 },
 {
   "zone_id": 284,
   "country_code": "PA",
   "zone_name": "America/Panama"
 },
 {
   "zone_id": 285,
   "country_code": "PE",
   "zone_name": "America/Lima"
 },
 {
   "zone_id": 286,
   "country_code": "PF",
   "zone_name": "Pacific/Tahiti"
 },
 {
   "zone_id": 287,
   "country_code": "PF",
   "zone_name": "Pacific/Marquesas"
 },
 {
   "zone_id": 288,
   "country_code": "PF",
   "zone_name": "Pacific/Gambier"
 },
 {
   "zone_id": 289,
   "country_code": "PG",
   "zone_name": "Pacific/Port_Moresby"
 },
 {
   "zone_id": 290,
   "country_code": "PG",
   "zone_name": "Pacific/Bougainville"
 },
 {
   "zone_id": 291,
   "country_code": "PH",
   "zone_name": "Asia/Manila"
 },
 {
   "zone_id": 292,
   "country_code": "PK",
   "zone_name": "Asia/Karachi"
 },
 {
   "zone_id": 293,
   "country_code": "PL",
   "zone_name": "Europe/Warsaw"
 },
 {
   "zone_id": 294,
   "country_code": "PM",
   "zone_name": "America/Miquelon"
 },
 {
   "zone_id": 295,
   "country_code": "PN",
   "zone_name": "Pacific/Pitcairn"
 },
 {
   "zone_id": 296,
   "country_code": "PR",
   "zone_name": "America/Puerto_Rico"
 },
 {
   "zone_id": 297,
   "country_code": "PS",
   "zone_name": "Asia/Gaza"
 },
 {
   "zone_id": 298,
   "country_code": "PS",
   "zone_name": "Asia/Hebron"
 },
 {
   "zone_id": 299,
   "country_code": "PT",
   "zone_name": "Europe/Lisbon"
 },
 {
   "zone_id": 300,
   "country_code": "PT",
   "zone_name": "Atlantic/Madeira"
 },
 {
   "zone_id": 301,
   "country_code": "PT",
   "zone_name": "Atlantic/Azores"
 },
 {
   "zone_id": 302,
   "country_code": "PW",
   "zone_name": "Pacific/Palau"
 },
 {
   "zone_id": 303,
   "country_code": "PY",
   "zone_name": "America/Asuncion"
 },
 {
   "zone_id": 304,
   "country_code": "QA",
   "zone_name": "Asia/Qatar"
 },
 {
   "zone_id": 305,
   "country_code": "RE",
   "zone_name": "Indian/Reunion"
 },
 {
   "zone_id": 306,
   "country_code": "RO",
   "zone_name": "Europe/Bucharest"
 },
 {
   "zone_id": 307,
   "country_code": "RS",
   "zone_name": "Europe/Belgrade"
 },
 {
   "zone_id": 308,
   "country_code": "RU",
   "zone_name": "Europe/Kaliningrad"
 },
 {
   "zone_id": 309,
   "country_code": "RU",
   "zone_name": "Europe/Moscow"
 },
 {
   "zone_id": 310,
   "country_code": "RU",
   "zone_name": "Europe/Simferopol"
 },
 {
   "zone_id": 311,
   "country_code": "RU",
   "zone_name": "Europe/Volgograd"
 },
 {
   "zone_id": 312,
   "country_code": "RU",
   "zone_name": "Europe/Kirov"
 },
 {
   "zone_id": 313,
   "country_code": "RU",
   "zone_name": "Europe/Astrakhan"
 },
 {
   "zone_id": 314,
   "country_code": "RU",
   "zone_name": "Europe/Saratov"
 },
 {
   "zone_id": 315,
   "country_code": "RU",
   "zone_name": "Europe/Ulyanovsk"
 },
 {
   "zone_id": 316,
   "country_code": "RU",
   "zone_name": "Europe/Samara"
 },
 {
   "zone_id": 317,
   "country_code": "RU",
   "zone_name": "Asia/Yekaterinburg"
 },
 {
   "zone_id": 318,
   "country_code": "RU",
   "zone_name": "Asia/Omsk"
 },
 {
   "zone_id": 319,
   "country_code": "RU",
   "zone_name": "Asia/Novosibirsk"
 },
 {
   "zone_id": 320,
   "country_code": "RU",
   "zone_name": "Asia/Barnaul"
 },
 {
   "zone_id": 321,
   "country_code": "RU",
   "zone_name": "Asia/Tomsk"
 },
 {
   "zone_id": 322,
   "country_code": "RU",
   "zone_name": "Asia/Novokuznetsk"
 },
 {
   "zone_id": 323,
   "country_code": "RU",
   "zone_name": "Asia/Krasnoyarsk"
 },
 {
   "zone_id": 324,
   "country_code": "RU",
   "zone_name": "Asia/Irkutsk"
 },
 {
   "zone_id": 325,
   "country_code": "RU",
   "zone_name": "Asia/Chita"
 },
 {
   "zone_id": 326,
   "country_code": "RU",
   "zone_name": "Asia/Yakutsk"
 },
 {
   "zone_id": 327,
   "country_code": "RU",
   "zone_name": "Asia/Khandyga"
 },
 {
   "zone_id": 328,
   "country_code": "RU",
   "zone_name": "Asia/Vladivostok"
 },
 {
   "zone_id": 329,
   "country_code": "RU",
   "zone_name": "Asia/Ust-Nera"
 },
 {
   "zone_id": 330,
   "country_code": "RU",
   "zone_name": "Asia/Magadan"
 },
 {
   "zone_id": 331,
   "country_code": "RU",
   "zone_name": "Asia/Sakhalin"
 },
 {
   "zone_id": 332,
   "country_code": "RU",
   "zone_name": "Asia/Srednekolymsk"
 },
 {
   "zone_id": 333,
   "country_code": "RU",
   "zone_name": "Asia/Kamchatka"
 },
 {
   "zone_id": 334,
   "country_code": "RU",
   "zone_name": "Asia/Anadyr"
 },
 {
   "zone_id": 335,
   "country_code": "RW",
   "zone_name": "Africa/Kigali"
 },
 {
   "zone_id": 336,
   "country_code": "SA",
   "zone_name": "Asia/Riyadh"
 },
 {
   "zone_id": 337,
   "country_code": "SB",
   "zone_name": "Pacific/Guadalcanal"
 },
 {
   "zone_id": 338,
   "country_code": "SC",
   "zone_name": "Indian/Mahe"
 },
 {
   "zone_id": 339,
   "country_code": "SD",
   "zone_name": "Africa/Khartoum"
 },
 {
   "zone_id": 340,
   "country_code": "SE",
   "zone_name": "Europe/Stockholm"
 },
 {
   "zone_id": 341,
   "country_code": "SG",
   "zone_name": "Asia/Singapore"
 },
 {
   "zone_id": 342,
   "country_code": "SH",
   "zone_name": "Atlantic/St_Helena"
 },
 {
   "zone_id": 343,
   "country_code": "SI",
   "zone_name": "Europe/Ljubljana"
 },
 {
   "zone_id": 344,
   "country_code": "SJ",
   "zone_name": "Arctic/Longyearbyen"
 },
 {
   "zone_id": 345,
   "country_code": "SK",
   "zone_name": "Europe/Bratislava"
 },
 {
   "zone_id": 346,
   "country_code": "SL",
   "zone_name": "Africa/Freetown"
 },
 {
   "zone_id": 347,
   "country_code": "SM",
   "zone_name": "Europe/San_Marino"
 },
 {
   "zone_id": 348,
   "country_code": "SN",
   "zone_name": "Africa/Dakar"
 },
 {
   "zone_id": 349,
   "country_code": "SO",
   "zone_name": "Africa/Mogadishu"
 },
 {
   "zone_id": 350,
   "country_code": "SR",
   "zone_name": "America/Paramaribo"
 },
 {
   "zone_id": 351,
   "country_code": "SS",
   "zone_name": "Africa/Juba"
 },
 {
   "zone_id": 352,
   "country_code": "ST",
   "zone_name": "Africa/Sao_Tome"
 },
 {
   "zone_id": 353,
   "country_code": "SV",
   "zone_name": "America/El_Salvador"
 },
 {
   "zone_id": 354,
   "country_code": "SX",
   "zone_name": "America/Lower_Princes"
 },
 {
   "zone_id": 355,
   "country_code": "SY",
   "zone_name": "Asia/Damascus"
 },
 {
   "zone_id": 356,
   "country_code": "SZ",
   "zone_name": "Africa/Mbabane"
 },
 {
   "zone_id": 357,
   "country_code": "TC",
   "zone_name": "America/Grand_Turk"
 },
 {
   "zone_id": 358,
   "country_code": "TD",
   "zone_name": "Africa/Ndjamena"
 },
 {
   "zone_id": 359,
   "country_code": "TF",
   "zone_name": "Indian/Kerguelen"
 },
 {
   "zone_id": 360,
   "country_code": "TG",
   "zone_name": "Africa/Lome"
 },
 {
   "zone_id": 361,
   "country_code": "TH",
   "zone_name": "Asia/Bangkok"
 },
 {
   "zone_id": 362,
   "country_code": "TJ",
   "zone_name": "Asia/Dushanbe"
 },
 {
   "zone_id": 363,
   "country_code": "TK",
   "zone_name": "Pacific/Fakaofo"
 },
 {
   "zone_id": 364,
   "country_code": "TL",
   "zone_name": "Asia/Dili"
 },
 {
   "zone_id": 365,
   "country_code": "TM",
   "zone_name": "Asia/Ashgabat"
 },
 {
   "zone_id": 366,
   "country_code": "TN",
   "zone_name": "Africa/Tunis"
 },
 {
   "zone_id": 367,
   "country_code": "TO",
   "zone_name": "Pacific/Tongatapu"
 },
 {
   "zone_id": 368,
   "country_code": "TR",
   "zone_name": "Europe/Istanbul"
 },
 {
   "zone_id": 369,
   "country_code": "TT",
   "zone_name": "America/Port_of_Spain"
 },
 {
   "zone_id": 370,
   "country_code": "TV",
   "zone_name": "Pacific/Funafuti"
 },
 {
   "zone_id": 371,
   "country_code": "TW",
   "zone_name": "Asia/Taipei"
 },
 {
   "zone_id": 372,
   "country_code": "TZ",
   "zone_name": "Africa/Dar_es_Salaam"
 },
 {
   "zone_id": 373,
   "country_code": "UA",
   "zone_name": "Europe/Kiev"
 },
 {
   "zone_id": 374,
   "country_code": "UA",
   "zone_name": "Europe/Uzhgorod"
 },
 {
   "zone_id": 375,
   "country_code": "UA",
   "zone_name": "Europe/Zaporozhye"
 },
 {
   "zone_id": 376,
   "country_code": "UG",
   "zone_name": "Africa/Kampala"
 },
 {
   "zone_id": 377,
   "country_code": "UM",
   "zone_name": "Pacific/Midway"
 },
 {
   "zone_id": 378,
   "country_code": "UM",
   "zone_name": "Pacific/Wake"
 },
 {
   "zone_id": 379,
   "country_code": "US",
   "zone_name": "America/New_York"
 },
 {
   "zone_id": 380,
   "country_code": "US",
   "zone_name": "America/Detroit"
 },
 {
   "zone_id": 381,
   "country_code": "US",
   "zone_name": "America/Kentucky/Louisville"
 },
 {
   "zone_id": 382,
   "country_code": "US",
   "zone_name": "America/Kentucky/Monticello"
 },
 {
   "zone_id": 383,
   "country_code": "US",
   "zone_name": "America/Indiana/Indianapolis"
 },
 {
   "zone_id": 384,
   "country_code": "US",
   "zone_name": "America/Indiana/Vincennes"
 },
 {
   "zone_id": 385,
   "country_code": "US",
   "zone_name": "America/Indiana/Winamac"
 },
 {
   "zone_id": 386,
   "country_code": "US",
   "zone_name": "America/Indiana/Marengo"
 },
 {
   "zone_id": 387,
   "country_code": "US",
   "zone_name": "America/Indiana/Petersburg"
 },
 {
   "zone_id": 388,
   "country_code": "US",
   "zone_name": "America/Indiana/Vevay"
 },
 {
   "zone_id": 389,
   "country_code": "US",
   "zone_name": "America/Chicago"
 },
 {
   "zone_id": 390,
   "country_code": "US",
   "zone_name": "America/Indiana/Tell_City"
 },
 {
   "zone_id": 391,
   "country_code": "US",
   "zone_name": "America/Indiana/Knox"
 },
 {
   "zone_id": 392,
   "country_code": "US",
   "zone_name": "America/Menominee"
 },
 {
   "zone_id": 393,
   "country_code": "US",
   "zone_name": "America/North_Dakota/Center"
 },
 {
   "zone_id": 394,
   "country_code": "US",
   "zone_name": "America/North_Dakota/New_Salem"
 },
 {
   "zone_id": 395,
   "country_code": "US",
   "zone_name": "America/North_Dakota/Beulah"
 },
 {
   "zone_id": 396,
   "country_code": "US",
   "zone_name": "America/Denver"
 },
 {
   "zone_id": 397,
   "country_code": "US",
   "zone_name": "America/Boise"
 },
 {
   "zone_id": 398,
   "country_code": "US",
   "zone_name": "America/Phoenix"
 },
 {
   "zone_id": 399,
   "country_code": "US",
   "zone_name": "America/Los_Angeles"
 },
 {
   "zone_id": 400,
   "country_code": "US",
   "zone_name": "America/Anchorage"
 },
 {
   "zone_id": 401,
   "country_code": "US",
   "zone_name": "America/Juneau"
 },
 {
   "zone_id": 402,
   "country_code": "US",
   "zone_name": "America/Sitka"
 },
 {
   "zone_id": 403,
   "country_code": "US",
   "zone_name": "America/Metlakatla"
 },
 {
   "zone_id": 404,
   "country_code": "US",
   "zone_name": "America/Yakutat"
 },
 {
   "zone_id": 405,
   "country_code": "US",
   "zone_name": "America/Nome"
 },
 {
   "zone_id": 406,
   "country_code": "US",
   "zone_name": "America/Adak"
 },
 {
   "zone_id": 407,
   "country_code": "US",
   "zone_name": "Pacific/Honolulu"
 },
 {
   "zone_id": 408,
   "country_code": "UY",
   "zone_name": "America/Montevideo"
 },
 {
   "zone_id": 409,
   "country_code": "UZ",
   "zone_name": "Asia/Samarkand"
 },
 {
   "zone_id": 410,
   "country_code": "UZ",
   "zone_name": "Asia/Tashkent"
 },
 {
   "zone_id": 411,
   "country_code": "VA",
   "zone_name": "Europe/Vatican"
 },
 {
   "zone_id": 412,
   "country_code": "VC",
   "zone_name": "America/St_Vincent"
 },
 {
   "zone_id": 413,
   "country_code": "VE",
   "zone_name": "America/Caracas"
 },
 {
   "zone_id": 414,
   "country_code": "VG",
   "zone_name": "America/Tortola"
 },
 {
   "zone_id": 415,
   "country_code": "VI",
   "zone_name": "America/St_Thomas"
 },
 {
   "zone_id": 416,
   "country_code": "VN",
   "zone_name": "Asia/Ho_Chi_Minh"
 },
 {
   "zone_id": 417,
   "country_code": "VU",
   "zone_name": "Pacific/Efate"
 },
 {
   "zone_id": 418,
   "country_code": "WF",
   "zone_name": "Pacific/Wallis"
 },
 {
   "zone_id": 419,
   "country_code": "WS",
   "zone_name": "Pacific/Apia"
 },
 {
   "zone_id": 420,
   "country_code": "YE",
   "zone_name": "Asia/Aden"
 },
 {
   "zone_id": 421,
   "country_code": "YT",
   "zone_name": "Indian/Mayotte"
 },
 {
   "zone_id": 422,
   "country_code": "ZA",
   "zone_name": "Africa/Johannesburg"
 },
 {
   "zone_id": 423,
   "country_code": "ZM",
   "zone_name": "Africa/Lusaka"
 },
 {
   "zone_id": 424,
   "country_code": "ZW",
   "zone_name": "Africa/Harare"
 }
]